mwreverts/__init__.py
mwreverts/about.py
mwreverts/api.py
mwreverts/db.py
mwreverts/defaults.py
mwreverts/detector.py
mwreverts/dummy_checksum.py
mwreverts/functions.py
mwreverts/historical_dict.py
mwreverts/mwreverts.py
mwreverts/revert.py
mwreverts/tests/__init__.py
mwreverts/tests/test_detector.py
mwreverts/tests/test_functions.py
mwreverts/tests/test_historical_dict.py
mwreverts/utilities/__init__.py
mwreverts/utilities/dump2reverts.py
mwreverts/utilities/revdocs2reverts.py
mwreverts-0.1.5.dist-info/DESCRIPTION.rst
mwreverts-0.1.5.dist-info/METADATA
mwreverts-0.1.5.dist-info/RECORD
mwreverts-0.1.5.dist-info/WHEEL
mwreverts-0.1.5.dist-info/entry_points.txt
mwreverts-0.1.5.dist-info/metadata.json
mwreverts-0.1.5.dist-info/top_level.txt
