Metadata-Version: 2.0
Name: mwreverts
Version: 0.1.5
Summary: A set of utilities for detecting reverts in MediaWiki revisions.
Home-page: https://github.com/mediawiki-utilities/python-mwreverts
Author: Aaron Halfaker
Author-email: aaron.halfaker@gmail.com
License: MIT
Platform: UNKNOWN
